Metadata-Version: 2.1
Name: paucode
Version: 0.3
Summary: funciones de ayuda en trabajo como economista
Download-URL: https://github.com/paucode1/paucode
Author: Javier Choque Paucar
Author-email: choquepaucarj.social@gmail.com
License: MIT
Keywords: example
License-File: LICENSE
